lrange.py
lrange-1.0.0.dist-info/DESCRIPTION.rst
lrange-1.0.0.dist-info/METADATA
lrange-1.0.0.dist-info/RECORD
lrange-1.0.0.dist-info/WHEEL
lrange-1.0.0.dist-info/metadata.json
lrange-1.0.0.dist-info/top_level.txt
