Metadata-Version: 2.0
Name: lrange
Version: 1.0.0
Summary: lrange - unlimited xrange in pure Python
Home-page: http://github.com/zed/lrange/
Author: zed
Author-email: arn.zart+zed@gmail.com
License: MIT
Download-URL: http://pypi.python.org/packages/source/l/lrange/lrange-1.0.0.tar.gz
Platform: Windows
Platform: Linux
Platform: Solaris
Platform: Mac OS-X
Platform: Unix
Classifier: Development Status :: 5 - Production/Stable
Classifier: Intended Audience :: Developers
Classifier: License :: OSI Approved :: MIT License
Classifier: Operating System :: OS Independent
Classifier: Programming Language :: Python :: 2
Classifier: Programming Language :: Python :: 3
Classifier: Topic :: Software Development :: Libraries :: Python Modules
Provides: lrange
